panoptes/data/__init__.py
panoptes/data/observations.py
panoptes/data/search.py
panoptes/data/settings.py
panoptes/data/utils/cli/main.py
panoptes_data-0.2.3.dist-info/METADATA
panoptes_data-0.2.3.dist-info/WHEEL
panoptes_data-0.2.3.dist-info/entry_points.txt
panoptes_data-0.2.3.dist-info/licenses/AUTHORS.md
panoptes_data-0.2.3.dist-info/licenses/LICENSE.txt
panoptes_data-0.2.3.dist-info/RECORD
