Metadata-Version: 2.4
Name: panoptes-data
Version: 0.2.3
Summary: Tools for working with PANOPTES data.
Project-URL: Documentation, https://projectpanoptes.org/
Project-URL: Source, https://github.com/panoptes/panoptes-data/
Project-URL: Download, https://pypi.org/project/panoptes-data/#files
Author-email: Wilfred Tyler Gee <wtylergee@gmail.com>
License: The MIT License (MIT)
License-File: AUTHORS.md
License-File: LICENSE.txt
Keywords: astronomy,data,panoptes
Classifier: Development Status :: 4 - Beta
Classifier: License :: OSI Approved :: MIT License
Classifier: Operating System :: OS Independent
Classifier: Programming Language :: Python
Classifier: Programming Language :: Python :: 3
Classifier: Programming Language :: Python :: 3 :: Only
Classifier: Programming Language :: Python :: 3.12
Requires-Python: >=3.12
Requires-Dist: astropy
Requires-Dist: numpy
Requires-Dist: pandas
Requires-Dist: panoptes-utils[images]
Requires-Dist: pydantic
Requires-Dist: pydantic-settings
Requires-Dist: python-dateutil
Requires-Dist: rich[jupyter]
Requires-Dist: tabulate
Requires-Dist: tqdm
Requires-Dist: typer
